akadoc/__init__.py
akadoc/entities/__init__.py
akadoc/entities/bbox.py
akadoc-0.0.1.dist-info/LICENSE
akadoc-0.0.1.dist-info/METADATA
akadoc-0.0.1.dist-info/WHEEL
akadoc-0.0.1.dist-info/top_level.txt
akadoc-0.0.1.dist-info/RECORD
