Metadata-Version: 2.1
Name: akadoc
Version: 0.0.1
Summary: A small package to unify all the document AI services
Author-email: syan <syan.vn@gmail.com>
Project-URL: Homepage, https://github.com/syanng
Project-URL: Bug Tracker, https://github.com/syanng
Classifier: Programming Language :: Python :: 3
Classifier: License :: OSI Approved :: MIT License
Classifier: Operating System :: OS Independent
Requires-Python: >=3.7
License-File: LICENSE
